paystack/__init__.py
paystack/account.py
paystack/bank.py
paystack/charges.py
paystack/customers.py
paystack/errors.py
paystack/invoices.py
paystack/payment.py
paystack/plans.py
paystack/products.py
paystack/refund.py
paystack/settings.py
paystack/settlements.py
paystack/subscription.py
paystack/transaction.py
paystack/transfers.py
paystack/util.py
paystack/verification.py
paystack/tests/__init__.py
paystack/tests/test_account.py
paystack/tests/test_bank.py
paystack/tests/test_charges.py
paystack/tests/test_customers.py
paystack/tests/test_invoices.py
paystack/tests/test_payment.py
paystack/tests/test_plans.py
paystack/tests/test_products.py
paystack/tests/test_refund.py
paystack/tests/test_settlements.py
paystack/tests/test_subscription.py
paystack/tests/test_transaction.py
paystack/tests/test_transfers.py
paystack/tests/test_verification.py
bitmast_paystack-2023.1.1.dist-info/LICENSE.txt
bitmast_paystack-2023.1.1.dist-info/METADATA
bitmast_paystack-2023.1.1.dist-info/WHEEL
bitmast_paystack-2023.1.1.dist-info/top_level.txt
bitmast_paystack-2023.1.1.dist-info/RECORD
