Metadata-Version: 2.1
Name: bitmast-paystack
Version: 2023.1.1
Summary: Python wrapper for PayStack Gateway API
Author: frier17
Author-email: Bitmast Digital Services <bitmastdigital@gmail.com>
Maintainer: frier17
License: Apache License
Project-URL: repository, https://gitlab.com/frier17/pypaystack.git
Keywords: payment,bank,card,account,PayStack,fintech
Classifier: Development Status :: 4 - Beta
Classifier: Programming Language :: Python
Requires-Python: >=3.7
License-File: LICENSE.txt
Requires-Dist: requests
Requires-Dist: dotenv
